telepot/__init__.py
telepot/api.py
telepot/delegate.py
telepot/exception.py
telepot/filtering.py
telepot/hack.py
telepot/helper.py
telepot/loop.py
telepot/namedtuple.py
telepot/routing.py
telepot/text.py
telepot/aio/__init__.py
telepot/aio/api.py
telepot/aio/delegate.py
telepot/aio/hack.py
telepot/aio/helper.py
telepot/aio/loop.py
telepot/aio/routing.py
telepot_x-12.8.dist-info/LICENSE.md
telepot_x-12.8.dist-info/METADATA
telepot_x-12.8.dist-info/WHEEL
telepot_x-12.8.dist-info/top_level.txt
telepot_x-12.8.dist-info/RECORD
