Metadata-Version: 2.1
Name: telepot-x
Version: 12.8
Summary: Python framework for Telegram Bot API
Home-page: https://github.com/cpcchengt/telepot
Author: cpcchengt
Author-email: chengt@cpchain.io
License: MIT
Keywords: telegram bot api python wrapper
Platform: UNKNOWN
Classifier: Development Status :: 5 - Production/Stable
Classifier: Intended Audience :: Developers
Classifier: Topic :: Software Development :: Libraries :: Python Modules
Classifier: Topic :: Communications :: Chat
Classifier: License :: OSI Approved :: MIT License
Classifier: Programming Language :: Python :: 2.7
Classifier: Programming Language :: Python :: 3
Classifier: Programming Language :: Python :: 3.2
Classifier: Programming Language :: Python :: 3.3
Classifier: Programming Language :: Python :: 3.4
Classifier: Programming Language :: Python :: 3.5
Classifier: Programming Language :: Python :: 3.6
Classifier: Programming Language :: Python :: 3.7
Classifier: Programming Language :: Python :: 3.8
Classifier: Programming Language :: Python :: 3.9
License-File: LICENSE.md
Requires-Dist: urllib3 (>=1.9.1)
Requires-Dist: aiohttp (>=3.0.0)
